{
  "15HC8U": {
    "pw": "9282",
    "hash": "a6ebcb693e",
    "filehash": "b713182f9f4c6efd",
    "viewer_url": "http://210.95.181.17:8101/hdv/view/?file_path=__upload/29/76/17511823637/2. 물품 관리전환 합의서(인재개발원).hwp&ext_to=pdf"
  },
  "W5J9XZ": {
    "pw": "3110",
    "hash": "524beeec87",
    "filehash": "d526e9334a8dbab2",
    "viewer_url": "http://210.95.181.17:8101/hdv/view/?file_path=__upload/25/07/17511844800/청양식당.txt&ext_to=pdf"
  },
  "TSYC4U": {
    "pw": "2662",
    "hash": "61b1dbc919",
    "filehash": "41e3aa0957884665",
    "viewer_url": "http://210.95.181.17:8101/hdv/view/?file_path=__upload/32/87/17511844998/(충남 인터넷)335.2025년도 DBMS 진단 결과 보고서.xlsx&ext_to=pdf"
  }
}